othello/__init__.py
othello/__main__.py
othello/agent/__init__.py
othello/agent/base.py
othello/agent/human.py
othello/agent/random_bot.py
othello/game/__init__.py
othello/game/board.py
othello/game/disc.py
othello/game/game_state.py
othello/game/move.py
othello/game/player.py
othello/game/point.py
othello_cli-0.1.0.dist-info/entry_points.txt
othello_cli-0.1.0.dist-info/LICENSE
othello_cli-0.1.0.dist-info/WHEEL
othello_cli-0.1.0.dist-info/METADATA
othello_cli-0.1.0.dist-info/RECORD
