Metadata-Version: 2.1
Name: othello-cli
Version: 0.1.0
Summary: CLI Othello with bots
Home-page: https://github.com/ahlaw/othello
License: MIT
Keywords: othello
Author: Amos Law
Author-email: amos.law98@gmail.com
Requires-Python: >=3.7,<4.0
Classifier: License :: OSI Approved :: MIT License
Classifier: Programming Language :: Python :: 3
Classifier: Programming Language :: Python :: 3.7
Classifier: Programming Language :: Python :: 3.8
Requires-Dist: importlib_metadata (>=1.6.0,<2.0.0); python_version < "3.8"
Project-URL: Repository, https://github.com/ahlaw/othello
